SeriesMaster/CricketAnalizer.py
SeriesMaster/HardCodeSer.py
SeriesMaster/ImageSer.py
SeriesMaster/NewRecruitment.py
SeriesMaster/PatternSer.py
SeriesMaster/__init__.py
SeriesMaster/readme.py
SeriesMaster/MathSer/BasicOperationsOnMathSer.py
SeriesMaster/MathSer/BonAcci.py
SeriesMaster/MathSer/ExponentialSer.py
SeriesMaster/MathSer/Factors.py
SeriesMaster/MathSer/LucasSer.py
SeriesMaster/MathSer/PasTri.py
SeriesMaster/MathSer/PrimeNumbers.py
SeriesMaster/MathSer/ProgSer.py
SeriesMaster/MathSer/__init__.py
SeriesMaster-0.2.2.dist-info/METADATA
SeriesMaster-0.2.2.dist-info/WHEEL
SeriesMaster-0.2.2.dist-info/entry_points.txt
SeriesMaster-0.2.2.dist-info/top_level.txt
SeriesMaster-0.2.2.dist-info/RECORD
