Metadata-Version: 2.1
Name: SeriesMaster
Version: 0.2.2
Summary: A Python library for various mathematical series operations
Author: Aditya
Classifier: Programming Language :: Python :: 3
Classifier: License :: OSI Approved :: MIT License
Classifier: Operating System :: OS Independent
Requires-Python: >=3.6
Requires-Dist: matplotlib
Requires-Dist: P
